{
  "type": "minecraft:crafting_shapeless",
  "ingredients": [
    {
      "tag": "forge:sand/colorless"
    },
    {
      "tag": "forge:sand/colorless"
    },
    {
      "tag": "forge:sand/colorless"
    },
    {
      "tag": "forge:sand/colorless"
    },
    {
      "tag": "forge:sand/colorless"
    },
    {
      "tag": "forge:sand/colorless"
    },
    {
      "tag": "forge:sand/colorless"
    },
    {
      "tag": "forge:sand/colorless"
    },
    {
      "tag": "forge:sand/colorless"
    }
  ],
  "result": {
    "item": "compacted:compacted_sand"
  }
}