{
  "type": "minecraft:crafting_shapeless",
  "ingredients": [
    {
      "item": "compacted:compacted_dirt"
    },
    {
      "item": "compacted:compacted_dirt"
    },
    {
      "item": "compacted:compacted_dirt"
    },
    {
      "item": "compacted:compacted_dirt"
    },
    {
      "item": "compacted:compacted_dirt"
    },
    {
      "item": "compacted:compacted_dirt"
    },
    {
      "item": "compacted:compacted_dirt"
    },
    {
      "item": "compacted:compacted_dirt"
    },
    {
      "item": "compacted:compacted_dirt"
    }
  ],
  "result": {
    "item": "compacted:double_compacted_dirt"
  }
}